CHANGELOG.txt
LICENCE.txt
MANIFEST.in
README.txt
setup.py
KunAction/__init__.py
kunpackage.egg-info/PKG-INFO
kunpackage.egg-info/SOURCES.txt
kunpackage.egg-info/dependency_links.txt
kunpackage.egg-info/top_level.txt