Metadata-Version: 1.1
Name: kunpackage
Version: 0.0.1
Summary: A very basic action package
Home-page: UNKNOWN
Author: Kun Zhang
Author-email: kuzhang@paloaltonetworks.com
License: MIT
Keywords: test
Platform: UNKNOWN
Classifier: Development Status :: 5 - Production/Stable
Classifier: Intended Audience :: Education
Classifier: Operating System :: Microsoft :: Windows :: Windows 10
Classifier: License :: OSI Approved :: MIT License
Classifier: Programming Language :: Python :: 3
